MANIFEST.in
setup.py
adminbrowse/__init__.py
adminbrowse/admin.py
adminbrowse/base.py
adminbrowse/columns.py
adminbrowse/models.py
adminbrowse/related.py
adminbrowse/tests.py
adminbrowse/views.py
adminbrowse/fixtures/test_adminbrowse.json
adminbrowse/media/css/adminbrowse.css
adminbrowse/media/images/find-faded.png
adminbrowse/media/images/find.png
adminbrowse/media/images/goto-faded.png
adminbrowse/media/images/goto.png
adminbrowse/media/images/link-external.png
adminbrowse/templates/adminbrowse/link_to_change.html
adminbrowse/templates/adminbrowse/link_to_changelist.html
django_adminbrowse.egg-info/PKG-INFO
django_adminbrowse.egg-info/SOURCES.txt
django_adminbrowse.egg-info/dependency_links.txt
django_adminbrowse.egg-info/top_level.txt