Metadata-Version: 1.0
Name: django-adminbrowse
Version: 0.1.2
Summary: Add related object links and other useful info to the Django admin interface
Home-page: https://github.com/exogen/django-adminbrowse
Author: Brian Beck
Author-email: exogen@gmail.com
License: MIT
Keywords: django admin changelist
Platform: UNKNOWN
